controller.v
module controller
(
    input wire clk, reset,
    output reg [6:0] A, B,
    output reg OP
);

reg [2:0] pstate, nstate;
parameter [2:0] START = 3'b000,
                ONE   = 3'b001,
                TWO   = 3'b010,
                THREE = 3'b011,
                FINISH = 3'b100;

always @(posedge clk or posedge reset)
begin
    if (reset)
        pstate <= START;
    else
        pstate <= nstate;
end

always @(*)
begin
    
    A = 7'b0000000;
    B = 7'b0000000;
    OP = 1'b0;

    nstate = pstate;

    case (pstate)
        START:
            nstate = ONE;
        ONE:
        begin
            A = 7'b1001000;
            B = 7'b1111010;
            OP = 1'b0;
            nstate = TWO;
        end
        TWO:
        begin
            A = 7'b0111001;
            B = 7'b0000110;
            OP = 1'b0;
            nstate = THREE;
        end
        THREE:
        begin
            A = 7'b0000010;
            B = 7'b0000010;
            OP = 1'b1;
            nstate = FINISH;
        end
        FINISH:
        begin    
            nstate = START;
        end  
  
        default: nstate = START;
    endcase
end

endmodule

controller_tb.v
`timescale 1ns/1ns
module controller_tb;
reg clk, reset;
wire [6:0] A, B;
wire OP;

controller uut (
    .clk(clk),
    .reset(reset),
    .A(A),
    .B(B),
    .OP(OP)
);

initial begin
    clk = 0;
    forever #5 clk = ~clk;
end

initial begin
    $dumpfile("controller_test.vcd");
    $dumpvars(0, controller_tb);
    reset = 1;    #10;
    reset = 0;    #55;
    $finish;
end

endmodule

controller_test.vcd
$date
	Fri Jun 13 02:14:56 2025
$end
$version
	Icarus Verilog
$end
$timescale
	1ns
$end
$scope module controller_tb $end
$var wire 1 ! OP $end
$var wire 7 " B [6:0] $end
$var wire 7 # A [6:0] $end
$var reg 1 $ clk $end
$var reg 1 % reset $end
$scope module uut $end
$var wire 1 $ clk $end
$var wire 1 % reset $end
$var parameter 3 & FINISH $end
$var parameter 3 ' ONE $end
$var parameter 3 ( START $end
$var parameter 3 ) THREE $end
$var parameter 3 * TWO $end
$var reg 7 + A [6:0] $end
$var reg 7 , B [6:0] $end
$var reg 1 ! OP $end
$var reg 3 - nstate [2:0] $end
$var reg 3 . pstate [2:0] $end
$upscope $end
$upscope $end
$enddefinitions $end
$comment Show the parameter values. $end
$dumpall
b10 *
b11 )
b0 (
b1 '
b100 &
$end
#0
$dumpvars
b0 .
b1 -
b0 ,
b0 +
1%
0$
b0 #
b0 "
0!
$end
#5
1$
#10
0$
0%
#15
b10 -
b1111010 "
b1111010 ,
b1001000 #
b1001000 +
b1 .
1$
#20
0$
#25
b11 -
b110 "
b110 ,
b111001 #
b111001 +
b10 .
1$
#30
0$
#35
b100 -
1!
b10 "
b10 ,
b10 #
b10 +
b11 .
1$
#40
0$
#45
b0 -
0!
b0 "
b0 ,
b0 #
b0 +
b100 .
1$
#50
0$
#55
b1 -
b0 .
1$
#60
0$
#65
b10 -
b1111010 "
b1111010 ,
b1001000 #
b1001000 +
b1 .
1$
