ALU_ROR_7bit.v
module ALU_ROR_7bit
(
    input [6:0] in,
    input [2:0] shift,
    output reg [6:0] out
);

always @(*) begin
    
    case(shift)
        3'b000: out = in;
        3'b001: out = {in[0], in[6:1]};
        3'b010: out = {in[1:0], in[6:2]};
        3'b011: out = {in[2:0], in[6:3]};
        3'b100: out = {in[3:0], in[6:4]};
        3'b101: out = {in[4:0], in[6:5]};
        3'b110: out = {in[5:0], in[6]};
        3'b111: out = in;
    endcase
end

endmodule

ALU_NOR_7bit.v
module ALU_NOR_7bit
(
    input wire [6:0] A,B,  
    output wire [6:0] result
);

assign result = ~(A | B);

endmodule

ALU.v
module ALU
(
    input wire [6:0] A, B,                   
    input wire OP,    
    output reg [6:0] result,     
    output wire CF,
    output wire SF,
    output wire ZF           
);

    wire [6:0] R_NOR, R_ROR;

    // Instantiate modules
    ALU_NOR_7bit NOR1 ( .A(A), .B(B), .result(R_NOR));
    ALU_ROR_7bit ROR1 ( .in(A), .shift(B[2:0]), .out(R_ROR));  // last 3 bits of input B

    always @(*) 
    begin
        case (OP)
            1'b0: // NOR 
                begin 
                    result = R_NOR; 
                end
            1'b1: // ROR
                begin 
                    
                    result = R_ROR;
                end
            
            default: 
                begin
                    result = 7'b0000000;  
                end
        endcase
    end

    assign CF = 1'b0;
    assign SF = result[6];
    assign ZF = ~(result[6] | result[5] | result[4] | result[3] | result[2] | result[1] | result[0]);

endmodule

controller.v
module controller
(
    input wire clk, reset,
    output reg [6:0] A, B,
    output reg OP
);

reg [2:0] pstate, nstate;
parameter [2:0] START = 3'b000,
                ONE   = 3'b001,
                TWO   = 3'b010,
                THREE = 3'b011,
                FINISH = 3'b100;

always @(posedge clk or posedge reset)
begin
    if (reset)
        pstate <= START;
    else
        pstate <= nstate;
end

always @(*)
begin
    
    A = 7'b0000000;
    B = 7'b0000000;
    OP = 1'b0;

    nstate = pstate;

    case (pstate)
        START:
            nstate = ONE;
        ONE:
        begin
            A = 7'b1001000;
            B = 7'b1111010;
            OP = 1'b0;
            nstate = TWO;
        end
        TWO:
        begin
            A = 7'b0111001;
            B = 7'b0000110;
            OP = 1'b0;
            nstate = THREE;
        end
        THREE:
        begin
            A = 7'b0000010;
            B = 7'b0000010;
            OP = 1'b1;
            nstate = FINISH;
        end
        FINISH:
        begin    
            nstate = START;
        end  
  
        default: nstate = START;
    endcase
end

endmodule

top.v
module top
(
    input wire clk, reset,
    output wire [6:0] result,
    output wire gt_zero
);
wire [6:0] A, B;
wire OP;
wire [6:0] R_result;
wire R_ZF;

controller controller1 (
    .clk(clk),
    .reset(reset),
    .A(A),
    .B(B),
    .OP(OP)
);
ALU datapath1 (
    .A(A),
    .B(B),
    .OP(OP),
    .result(R_result),
    .ZF(R_ZF)
);

assign result = R_result;
assign gt_zero = ~R_ZF;


endmodule

top_tb.v
`timescale 1ns/1ns
module top_tb;

reg clk, reset;
wire [6:0] result;
wire gt_zero;

top uut (
    .clk(clk),
    .reset(reset),
    .result(result),
    .gt_zero(gt_zero)
);

initial begin
    clk = 0;
    forever #5 clk = ~clk;
end

initial begin
    $dumpfile("top_test.vcd");
    $dumpvars(0, top_tb);
    reset = 1;  #15;
    reset = 0;  #60;
    $finish;
end

endmodule

top_test.vcd
$date
	Fri Jun 13 02:16:30 2025
$end
$version
	Icarus Verilog
$end
$timescale
	1ns
$end
$scope module top_tb $end
$var wire 7 ! result [6:0] $end
$var wire 1 " gt_zero $end
$var reg 1 # clk $end
$var reg 1 $ reset $end
$scope module uut $end
$var wire 1 # clk $end
$var wire 1 " gt_zero $end
$var wire 1 $ reset $end
$var wire 7 % result [6:0] $end
$var wire 7 & R_result [6:0] $end
$var wire 1 ' R_ZF $end
$var wire 1 ( OP $end
$var wire 7 ) B [6:0] $end
$var wire 7 * A [6:0] $end
$scope module controller1 $end
$var wire 1 # clk $end
$var wire 1 $ reset $end
$var parameter 3 + FINISH $end
$var parameter 3 , ONE $end
$var parameter 3 - START $end
$var parameter 3 . THREE $end
$var parameter 3 / TWO $end
$var reg 7 0 A [6:0] $end
$var reg 7 1 B [6:0] $end
$var reg 1 ( OP $end
$var reg 3 2 nstate [2:0] $end
$var reg 3 3 pstate [2:0] $end
$upscope $end
$scope module datapath1 $end
$var wire 7 4 A [6:0] $end
$var wire 7 5 B [6:0] $end
$var wire 1 6 CF $end
$var wire 1 ( OP $end
$var wire 1 ' ZF $end
$var wire 1 7 SF $end
$var wire 7 8 R_ROR [6:0] $end
$var wire 7 9 R_NOR [6:0] $end
$var reg 7 : result [6:0] $end
$scope module NOR1 $end
$var wire 7 ; A [6:0] $end
$var wire 7 < B [6:0] $end
$var wire 7 = result [6:0] $end
$upscope $end
$scope module ROR1 $end
$var wire 7 > in [6:0] $end
$var wire 3 ? shift [2:0] $end
$var reg 7 @ out [6:0] $end
$upscope $end
$upscope $end
$upscope $end
$upscope $end
$enddefinitions $end
$comment Show the parameter values. $end
$dumpall
b10 /
b11 .
b0 -
b1 ,
b100 +
$end
#0
$dumpvars
b0 @
b0 ?
b0 >
b1111111 =
b0 <
b0 ;
b1111111 :
b1111111 9
b0 8
17
06
b0 5
b0 4
b0 3
b1 2
b0 1
b0 0
b0 *
b0 )
0(
0'
b1111111 &
b1111111 %
1$
0#
1"
b1111111 !
$end
#5
1#
#10
0#
#15
07
b101 !
b101 %
b101 &
b101 :
b101 9
b101 =
b10 ?
b10010 8
b10010 @
b10 2
b1111010 )
b1111010 1
b1111010 5
b1111010 <
b1001000 *
b1001000 0
b1001000 4
b1001000 ;
b1001000 >
b1 3
1#
0$
#20
0#
#25
1"
0'
17
b1000000 !
b1000000 %
b1000000 &
b1000000 :
b1000000 9
b1000000 =
b110 ?
b1110010 8
b1110010 @
b11 2
b110 )
b110 1
b110 5
b110 <
b111001 *
b111001 0
b111001 4
b111001 ;
b111001 >
b10 3
1#
#30
0#
#35
1"
0'
17
b1111101 9
b1111101 =
b1000000 !
b1000000 %
b1000000 &
b1000000 :
b10 ?
b1000000 8
b1000000 @
b100 2
1(
b10 )
b10 1
b10 5
b10 <
b10 *
b10 0
b10 4
b10 ;
b10 >
b11 3
1#
#40
0#
#45
b1111111 9
b1111111 =
b1111111 !
b1111111 %
b1111111 &
b1111111 :
b0 ?
b0 8
b0 @
b0 2
0(
b0 )
b0 1
b0 5
b0 <
b0 *
b0 0
b0 4
b0 ;
b0 >
b100 3
1#
#50
0#
#55
b1 2
b0 3
1#
#60
0#
#65
07
b101 !
b101 %
b101 &
b101 :
b101 9
b101 =
b10 ?
b10010 8
b10010 @
b10 2
b1111010 )
b1111010 1
b1111010 5
b1111010 <
b1001000 *
b1001000 0
b1001000 4
b1001000 ;
b1001000 >
b1 3
1#
#70
0#
#75
1"
0'
17
b1000000 !
b1000000 %
b1000000 &
b1000000 :
b1000000 9
b1000000 =
b110 ?
b1110010 8
b1110010 @
b11 2
b110 )
b110 1
b110 5
b110 <
b111001 *
b111001 0
b111001 4
b111001 ;
b111001 >
b10 3
1#
